{"assembly":{".code":[{"begin":23434,"end":24089,"name":"PUSH","value":"80"},{"begin":23434,"end":24089,"name":"PUSH","value":"40"},{"begin":23434,"end":24089,"name":"MSTORE"},{"begin":23592,"end":23647,"name":"CALLVALUE"},{"begin":8,"end":17,"name":"DUP1"},{"begin":5,"end":7,"name":"ISZERO"},{"begin":5,"end":7,"name":"PUSH [tag]","value":"1"},{"begin":5,"end":7,"name":"JUMPI"},{"begin":30,"end":31,"name":"PUSH","value":"0"},{"begin":27,"end":28,"name":"DUP1"},{"begin":20,"end":32,"name":"REVERT"},{"begin":5,"end":7,"name":"tag","value":"1"},{"begin":5,"end":7,"name":"JUMPDEST"},{"begin":-1,"end":-1,"name":"POP"},{"begin":23624,"end":23629,"name":"PUSH","value":"0"},{"begin":23624,"end":23642,"name":"DUP1"},{"begin":23624,"end":23642,"name":"SLOAD"},{"begin":-1,"end":-1,"name":"PUSH","value":"1"},{"begin":-1,"end":-1,"name":"PUSH","value":"A0"},{"begin":-1,"end":-1,"name":"PUSH","value":"2"},{"begin":-1,"end":-1,"name":"EXP"},{"begin":-1,"end":-1,"name":"SUB"},{"begin":-1,"end":-1,"name":"NOT"},{"begin":23624,"end":23642,"name":"AND"},{"begin":23632,"end":23642,"name":"CALLER"},{"begin":23624,"end":23642,"name":"OR"},{"begin":23624,"end":23642,"name":"SWAP1"},{"begin":23624,"end":23642,"name":"SSTORE"},{"begin":23434,"end":24089,"name":"PUSH #[$]","value":"0000000000000000000000000000000000000000000000000000000000000000"},{"begin":23434,"end":24089,"name":"DUP1"},{"begin":23434,"end":24089,"name":"PUSH [$]","value":"0000000000000000000000000000000000000000000000000000000000000000"},{"begin":23434,"end":24089,"name":"PUSH","value":"0"},{"begin":23434,"end":24089,"name":"CODECOPY"},{"begin":23434,"end":24089,"name":"PUSH","value":"0"},{"begin":23434,"end":24089,"name":"RETURN"}],".data":{"0":{".auxdata":"a165627a7a72305820e3130d353235588c65bcb6f7ab24fe1faec57184fd21f8c3fcc631871f75480f0029",".code":[{"begin":23434,"end":24089,"name":"PUSH","value":"80"},{"begin":23434,"end":24089,"name":"PUSH","value":"40"},{"begin":23434,"end":24089,"name":"MSTORE"},{"begin":23434,"end":24089,"name":"PUSH","value":"4"},{"begin":23434,"end":24089,"name":"CALLDATASIZE"},{"begin":23434,"end":24089,"name":"LT"},{"begin":23434,"end":24089,"name":"PUSH [tag]","value":"1"},{"begin":23434,"end":24089,"name":"JUMPI"},{"begin":23434,"end":24089,"name":"PUSH","value":"FFFFFFFF"},{"begin":23434,"end":24089,"name":"PUSH","value":"100000000000000000000000000000000000000000000000000000000"},{"begin":23434,"end":24089,"name":"PUSH","value":"0"},{"begin":23434,"end":24089,"name":"CALLDATALOAD"},{"begin":23434,"end":24089,"name":"DIV"},{"begin":23434,"end":24089,"name":"AND"},{"begin":23434,"end":24089,"name":"PUSH","value":"8DA5CB5B"},{"begin":23434,"end":24089,"name":"DUP2"},{"begin":23434,"end":24089,"name":"EQ"},{"begin":23434,"end":24089,"name":"PUSH [tag]","value":"2"},{"begin":23434,"end":24089,"name":"JUMPI"},{"begin":23434,"end":24089,"name":"DUP1"},{"begin":23434,"end":24089,"name":"PUSH","value":"F2FDE38B"},{"begin":23434,"end":24089,"name":"EQ"},{"begin":23434,"end":24089,"name":"PUSH [tag]","value":"3"},{"begin":23434,"end":24089,"name":"JUMPI"},{"begin":23434,"end":24089,"name":"tag","value":"1"},{"begin":23434,"end":24089,"name":"JUMPDEST"},{"begin":23434,"end":24089,"name":"PUSH","value":"0"},{"begin":23434,"end":24089,"name":"DUP1"},{"begin":23434,"end":24089,"name":"REVERT"},{"begin":23455,"end":23475,"name":"tag","value":"2"},{"begin":23455,"end":23475,"name":"JUMPDEST"},{"begin":23455,"end":23475,"name":"CALLVALUE"},{"begin":8,"end":17,"name":"DUP1"},{"begin":5,"end":7,"name":"ISZERO"},{"begin":5,"end":7,"name":"PUSH [tag]","value":"4"},{"begin":5,"end":7,"name":"JUMPI"},{"begin":30,"end":31,"name":"PUSH","value":"0"},{"begin":27,"end":28,"name":"DUP1"},{"begin":20,"end":32,"name":"REVERT"},{"begin":5,"end":7,"name":"tag","value":"4"},{"begin":5,"end":7,"name":"JUMPDEST"},{"begin":23455,"end":23475,"name":"POP"},{"begin":23455,"end":23475,"name":"PUSH [tag]","value":"5"},{"begin":23455,"end":23475,"name":"PUSH [tag]","value":"6"},{"begin":23455,"end":23475,"name":"JUMP"},{"begin":23455,"end":23475,"name":"tag","value":"5"},{"begin":23455,"end":23475,"name":"JUMPDEST"},{"begin":23455,"end":23475,"name":"PUSH","value":"40"},{"begin":23455,"end":23475,"name":"DUP1"},{"begin":23455,"end":23475,"name":"MLOAD"},{"begin":23455,"end":23475,"name":"PUSH","value":"FFFFFFFFFFFFFFFFFFFFFFFFFFFFFFFFFFFFFFFF"},{"begin":23455,"end":23475,"name":"SWAP1"},{"begin":23455,"end":23475,"name":"SWAP3"},{"begin":23455,"end":23475,"name":"AND"},{"begin":23455,"end":23475,"name":"DUP3"},{"begin":23455,"end":23475,"name":"MSTORE"},{"begin":23455,"end":23475,"name":"MLOAD"},{"begin":23455,"end":23475,"name":"SWAP1"},{"begin":23455,"end":23475,"name":"DUP2"},{"begin":23455,"end":23475,"name":"SWAP1"},{"begin":23455,"end":23475,"name":"SUB"},{"begin":23455,"end":23475,"name":"PUSH","value":"20"},{"begin":23455,"end":23475,"name":"ADD"},{"begin":23455,"end":23475,"name":"SWAP1"},{"begin":23455,"end":23475,"name":"RETURN"},{"begin":23955,"end":24086,"name":"tag","value":"3"},{"begin":23955,"end":24086,"name":"JUMPDEST"},{"begin":23955,"end":24086,"name":"CALLVALUE"},{"begin":8,"end":17,"name":"DUP1"},{"begin":5,"end":7,"name":"ISZERO"},{"begin":5,"end":7,"name":"PUSH [tag]","value":"7"},{"begin":5,"end":7,"name":"JUMPI"},{"begin":30,"end":31,"name":"PUSH","value":"0"},{"begin":27,"end":28,"name":"DUP1"},{"begin":20,"end":32,"name":"REVERT"},{"begin":5,"end":7,"name":"tag","value":"7"},{"begin":5,"end":7,"name":"JUMPDEST"},{"begin":-1,"end":-1,"name":"POP"},{"begin":23955,"end":24086,"name":"PUSH [tag]","value":"8"},{"begin":23955,"end":24086,"name":"PUSH","value":"FFFFFFFFFFFFFFFFFFFFFFFFFFFFFFFFFFFFFFFF"},{"begin":23955,"end":24086,"name":"PUSH","value":"4"},{"begin":23955,"end":24086,"name":"CALLDATALOAD"},{"begin":23955,"end":24086,"name":"AND"},{"begin":23955,"end":24086,"name":"PUSH [tag]","value":"9"},{"begin":23955,"end":24086,"name":"JUMP"},{"begin":23955,"end":24086,"name":"tag","value":"8"},{"begin":23955,"end":24086,"name":"JUMPDEST"},{"begin":23955,"end":24086,"name":"STOP"},{"begin":23455,"end":23475,"name":"tag","value":"6"},{"begin":23455,"end":23475,"name":"JUMPDEST"},{"begin":23455,"end":23475,"name":"PUSH","value":"0"},{"begin":23455,"end":23475,"name":"SLOAD"},{"begin":23455,"end":23475,"name":"PUSH","value":"FFFFFFFFFFFFFFFFFFFFFFFFFFFFFFFFFFFFFFFF"},{"begin":23455,"end":23475,"name":"AND"},{"begin":23455,"end":23475,"name":"DUP2"},{"begin":23455,"end":23475,"name":"JUMP","value":"[out]"},{"begin":23955,"end":24086,"name":"tag","value":"9"},{"begin":23955,"end":24086,"name":"JUMPDEST"},{"begin":23776,"end":23781,"name":"PUSH","value":"0"},{"begin":23776,"end":23781,"name":"SLOAD"},{"begin":23776,"end":23781,"name":"PUSH","value":"FFFFFFFFFFFFFFFFFFFFFFFFFFFFFFFFFFFFFFFF"},{"begin":23776,"end":23781,"name":"AND"},{"begin":23762,"end":23772,"name":"CALLER"},{"begin":23762,"end":23781,"name":"EQ"},{"begin":23754,"end":23782,"name":"PUSH [tag]","value":"11"},{"begin":23754,"end":23782,"name":"JUMPI"},{"begin":23754,"end":23782,"name":"PUSH","value":"0"},{"begin":23754,"end":23782,"name":"DUP1"},{"begin":23754,"end":23782,"name":"REVERT"},{"begin":23754,"end":23782,"name":"tag","value":"11"},{"begin":23754,"end":23782,"name":"JUMPDEST"},{"begin":24027,"end":24049,"name":"PUSH","value":"FFFFFFFFFFFFFFFFFFFFFFFFFFFFFFFFFFFFFFFF"},{"begin":24027,"end":24049,"name":"DUP2"},{"begin":24027,"end":24049,"name":"AND"},{"begin":24027,"end":24049,"name":"ISZERO"},{"begin":24023,"end":24082,"name":"PUSH [tag]","value":"13"},{"begin":24023,"end":24082,"name":"JUMPI"},{"begin":24059,"end":24064,"name":"PUSH","value":"0"},{"begin":24059,"end":24075,"name":"DUP1"},{"begin":24059,"end":24075,"name":"SLOAD"},{"begin":-1,"end":-1,"name":"PUSH","value":"FFFFFFFFFFFFFFFFFFFFFFFFFFFFFFFFFFFFFFFF"},{"begin":-1,"end":-1,"name":"NOT"},{"begin":24059,"end":24075,"name":"AND"},{"begin":24059,"end":24075,"name":"PUSH","value":"FFFFFFFFFFFFFFFFFFFFFFFFFFFFFFFFFFFFFFFF"},{"begin":24059,"end":24075,"name":"DUP4"},{"begin":24059,"end":24075,"name":"AND"},{"begin":24059,"end":24075,"name":"OR"},{"begin":24059,"end":24075,"name":"SWAP1"},{"begin":24059,"end":24075,"name":"SSTORE"},{"begin":24023,"end":24082,"name":"tag","value":"13"},{"begin":24023,"end":24082,"name":"JUMPDEST"},{"begin":23955,"end":24086,"name":"POP"},{"begin":23955,"end":24086,"name":"JUMP","value":"[out]"}]}}},"bytecode":"608060405234801561001057600080fd5b5060008054600160a060020a0319163317905561017f806100326000396000f30060806040526004361061004b5763ffffffff7c01000000000000000000000000000000000000000000000000000000006000350416638da5cb5b8114610050578063f2fde38b1461008e575b600080fd5b34801561005c57600080fd5b506100656100be565b6040805173ffffffffffffffffffffffffffffffffffffffff9092168252519081900360200190f35b34801561009a57600080fd5b506100bc73ffffffffffffffffffffffffffffffffffffffff600435166100da565b005b60005473ffffffffffffffffffffffffffffffffffffffff1681565b60005473ffffffffffffffffffffffffffffffffffffffff1633146100fe57600080fd5b73ffffffffffffffffffffffffffffffffffffffff811615610150576000805473ffffffffffffffffffffffffffffffffffffffff191673ffffffffffffffffffffffffffffffffffffffff83161790555b505600a165627a7a72305820e3130d353235588c65bcb6f7ab24fe1faec57184fd21f8c3fcc631871f75480f0029","functionHashes":{"owner()":"8da5cb5b","transferOwnership(address)":"f2fde38b"},"gasEstimates":{"creation":[20415,76600],"external":{"owner()":399,"transferOwnership(address)":20650},"internal":{}},"interface":"[{\"constant\":true,\"inputs\":[],\"name\":\"owner\",\"outputs\":[{\"name\":\"\",\"type\":\"address\"}],\"payable\":false,\"stateMutability\":\"view\",\"type\":\"function\"},{\"constant\":false,\"inputs\":[{\"name\":\"newOwner\",\"type\":\"address\"}],\"name\":\"transferOwnership\",\"outputs\":[],\"payable\":false,\"stateMutability\":\"nonpayable\",\"type\":\"function\"},{\"inputs\":[],\"payable\":false,\"stateMutability\":\"nonpayable\",\"type\":\"constructor\"}]","metadata":"{\"compiler\":{\"version\":\"0.4.24+commit.e67f0147\"},\"language\":\"Solidity\",\"output\":{\"abi\":[{\"constant\":true,\"inputs\":[],\"name\":\"owner\",\"outputs\":[{\"name\":\"\",\"type\":\"address\"}],\"payable\":false,\"stateMutability\":\"view\",\"type\":\"function\"},{\"constant\":false,\"inputs\":[{\"name\":\"newOwner\",\"type\":\"address\"}],\"name\":\"transferOwnership\",\"outputs\":[],\"payable\":false,\"stateMutability\":\"nonpayable\",\"type\":\"function\"},{\"inputs\":[],\"payable\":false,\"stateMutability\":\"nonpayable\",\"type\":\"constructor\"}],\"devdoc\":{\"methods\":{\"transferOwnership(address)\":{\"details\":\"Allows the current owner to transfer control of the contract to a newOwner.\",\"params\":{\"newOwner\":\"The address to transfer ownership to.\"}}},\"title\":\"Ownable\"},\"userdoc\":{\"methods\":{}}},\"settings\":{\"compilationTarget\":{\"\":\"Ownable\"},\"evmVersion\":\"byzantium\",\"libraries\":{},\"optimizer\":{\"enabled\":true,\"runs\":200},\"remappings\":[]},\"sources\":{\"\":{\"keccak256\":\"0x0360dda1565e3bef3ebb9c3cb3308e1b1924b2a77650eaef27713d9c2c53bc0f\",\"urls\":[\"bzzr://38c5cae6ad40860e6014e380e7ca56f6e4ecc3a3e21bad6ae3f1f8962b9adfec\"]}},\"version\":1}","opcodes":"PUSH1 0x80 PUSH1 0x40 MSTORE CALLVALUE DUP1 ISZERO PUSH2 0x10 JUMPI PUSH1 0x0 DUP1 REVERT JUMPDEST POP PUSH1 0x0 DUP1 SLOAD PUSH1 0x1 PUSH1 0xA0 PUSH1 0x2 EXP SUB NOT AND CALLER OR SWAP1 SSTORE PUSH2 0x17F DUP1 PUSH2 0x32 PUSH1 0x0 CODECOPY PUSH1 0x0 RETURN STOP PUSH1 0x80 PUSH1 0x40 MSTORE PUSH1 0x4 CALLDATASIZE LT PUSH2 0x4B JUMPI PUSH4 0xFFFFFFFF PUSH29 0x100000000000000000000000000000000000000000000000000000000 PUSH1 0x0 CALLDATALOAD DIV AND PUSH4 0x8DA5CB5B DUP2 EQ PUSH2 0x50 JUMPI DUP1 PUSH4 0xF2FDE38B EQ PUSH2 0x8E JUMPI JUMPDEST PUSH1 0x0 DUP1 REVERT JUMPDEST CALLVALUE DUP1 ISZERO PUSH2 0x5C JUMPI PUSH1 0x0 DUP1 REVERT JUMPDEST POP PUSH2 0x65 PUSH2 0xBE JUMP JUMPDEST PUSH1 0x40 DUP1 MLOAD PUSH20 0xFFFFFFFFFFFFFFFFFFFFFFFFFFFFFFFFFFFFFFFF SWAP1 SWAP3 AND DUP3 MSTORE MLOAD SWAP1 DUP2 SWAP1 SUB PUSH1 0x20 ADD SWAP1 RETURN JUMPDEST CALLVALUE DUP1 ISZERO PUSH2 0x9A JUMPI PUSH1 0x0 DUP1 REVERT JUMPDEST POP PUSH2 0xBC PUSH20 0xFFFFFFFFFFFFFFFFFFFFFFFFFFFFFFFFFFFFFFFF PUSH1 0x4 CALLDATALOAD AND PUSH2 0xDA JUMP JUMPDEST STOP JUMPDEST PUSH1 0x0 SLOAD PUSH20 0xFFFFFFFFFFFFFFFFFFFFFFFFFFFFFFFFFFFFFFFF AND DUP2 JUMP JUMPDEST PUSH1 0x0 SLOAD PUSH20 0xFFFFFFFFFFFFFFFFFFFFFFFFFFFFFFFFFFFFFFFF AND CALLER EQ PUSH2 0xFE JUMPI PUSH1 0x0 DUP1 REVERT JUMPDEST PUSH20 0xFFFFFFFFFFFFFFFFFFFFFFFFFFFFFFFFFFFFFFFF DUP2 AND ISZERO PUSH2 0x150 JUMPI PUSH1 0x0 DUP1 SLOAD PUSH20 0xFFFFFFFFFFFFFFFFFFFFFFFFFFFFFFFFFFFFFFFF NOT AND PUSH20 0xFFFFFFFFFFFFFFFFFFFFFFFFFFFFFFFFFFFFFFFF DUP4 AND OR SWAP1 SSTORE JUMPDEST POP JUMP STOP LOG1 PUSH6 0x627A7A723058 KECCAK256 0xe3 SGT 0xd CALLDATALOAD ORIGIN CALLDATALOAD PC DUP13 PUSH6 0xBCB6F7AB24FE 0x1f 0xae 0xc5 PUSH18 0x84FD21F8C3FCC631871F75480F0029000000 ","runtimeBytecode":"60806040526004361061004b5763ffffffff7c01000000000000000000000000000000000000000000000000000000006000350416638da5cb5b8114610050578063f2fde38b1461008e575b600080fd5b34801561005c57600080fd5b506100656100be565b6040805173ffffffffffffffffffffffffffffffffffffffff9092168252519081900360200190f35b34801561009a57600080fd5b506100bc73ffffffffffffffffffffffffffffffffffffffff600435166100da565b005b60005473ffffffffffffffffffffffffffffffffffffffff1681565b60005473ffffffffffffffffffffffffffffffffffffffff1633146100fe57600080fd5b73ffffffffffffffffffffffffffffffffffffffff811615610150576000805473ffffffffffffffffffffffffffffffffffffffff191673ffffffffffffffffffffffffffffffffffffffff83161790555b505600a165627a7a72305820e3130d353235588c65bcb6f7ab24fe1faec57184fd21f8c3fcc631871f75480f0029","srcmap":"23434:655:0:-;;;23592:55;8:9:-1;5:2;;;30:1;27;20:12;5:2;-1:-1;23624:5:0;:18;;-1:-1:-1;;;;;;23624:18:0;23632:10;23624:18;;;23434:655;;;;;;","srcmapRuntime":"23434:655:0:-;;;;;;;;;;;;;;;;;;;;;;;;;;;;23455:20;;8:9:-1;5:2;;;30:1;27;20:12;5:2;23455:20:0;;;;;;;;;;;;;;;;;;;;;;;23955:131;;8:9:-1;5:2;;;30:1;27;20:12;5:2;-1:-1;23955:131:0;;;;;;;;;23455:20;;;;;;:::o;23955:131::-;23776:5;;;;23762:10;:19;23754:28;;;;;;24027:22;;;;24023:59;;24059:5;:16;;-1:-1:-1;;24059:16:0;;;;;;;24023:59;23955:131;:::o"}
